proj/__init__.py
proj/main.py
crproj-0.0.1.dist-info/LICENSE
crproj-0.0.1.dist-info/METADATA
crproj-0.0.1.dist-info/WHEEL
crproj-0.0.1.dist-info/entry_points.txt
crproj-0.0.1.dist-info/top_level.txt
crproj-0.0.1.dist-info/RECORD
